<?xml version="1.0" encoding="UTF-8"?>
<tables>
	<table>
		<tablename>CoefficientKb</tablename>
		<postgretablename>ACCESS</postgretablename>
		<champs>
		<champ>
				<name>CodeEspece</name>
				<type>text</type>
				<postgrename>ACCESS</postgrename>
				<postgretype>ACCESS</postgretype>
			</champ>
			<champ>
				<name>IdSysteme</name>
				<type>integer</type>
				<postgrename>ACCESS</postgrename>
				<postgretype>ACCESS</postgretype>
			</champ>
			<champ>
				<name>CodeOrigineKb</name>
				<type>real</type>
				<postgrename>ACCESS</postgrename>
				<postgretype>ACCESS</postgretype>
			</champ>
			<champ>
				<name>CoefA</name>
				<type>real</type>
				<postgrename>ACCESS</postgrename>
				<postgretype>ACCESS</postgretype>
			</champ>
			<champ>
				<name>CoefB</name>
				<type>real</type>
				<postgrename>ACCESS</postgrename>
				<postgretype>ACCESS</postgretype>
			</champ>			
			<champ>
				<name>Renvoi</name>
				<type>integer</type>
				<postgrename>ACCESS</postgrename>
				<postgretype>ACCESS</postgretype>
			</champ>
			<champ>
				<name>RenvoiSyst</name>
				<type>integer</type>
				<postgrename>ACCESS</postgrename>
				<postgretype>ACCESS</postgretype>
			</champ>
			<champ>
				<name>ValeurConserve</name>
				<type>boolean</type>
				<postgrename>ACCESS</postgrename>
				<postgretype>ACCESS</postgretype>
			</champ>
		</champs>
	</table>
	<table>
		<tablename>TypeAgglomeration</tablename>
		<postgretablename>art_type_agglomeration</postgretablename>
		<champs>
			<champ>
				<name>IdTypeAgglo</name>
				<type>integer</type>
				<postgrename>id</postgrename>
				<postgretype>integer</postgretype>
			</champ>
			<champ>
				<name>LibelleTypeAgglo</name>
				<type>text</type>
				<postgrename>libelle</postgrename>
				<postgretype>text</postgretype>
			</champ>
		</champs>
	</table>
	<table>
		<tablename>TypeActivite</tablename>
		<postgretablename>art_type_activite</postgretablename>
		<champs>
			<champ>
				<name>NumTypeAct</name>
				<type>integer</type>
				<postgrename>id</postgrename>
				<postgretype>integer</postgretype>
			</champ>
			<champ>
				<name>LibelleAct</name>
				<type>text</type>
				<postgrename>libelle</postgrename>
				<postgretype>text</postgretype>
			</champ>
			<champ>
				<name>RaisonAct</name>
				<type>text</type>
				<postgrename>raison</postgrename>
				<postgretype>text</postgretype>
			</champ>
		</champs>
	</table>
	<table>
		<tablename>CategorieSocioProfessionnelle</tablename>
		<postgretablename>art_categorie_socio_professionnelle</postgretablename>
		<champs>
			<champ>
				<name>CodeCategorie</name>
				<type>integer</type>
				<postgrename>id</postgrename>
				<postgretype>integer</postgretype>
			</champ>
			<champ>
				<name>LibelleCategorie</name>
				<type>text</type>
				<postgrename>libelle</postgrename>
				<postgretype>text</postgretype>
			</champ>
		</champs>
	</table>	
	<table>
		<tablename>EtatCiel</tablename>
		<postgretablename>art_etat_ciel</postgretablename>
		<champs>
			<champ>
				<name>CodeEtatCiel</name>
				<type>integer</type>
				<postgrename>id</postgrename>
				<postgretype>integer</postgretype>
			</champ>
			<champ>
				<name>LibelleEtatCiel</name>
				<type>text</type>
				<postgrename>libelle</postgrename>
				<postgretype>text</postgretype>
			</champ>
		</champs>
	</table>	
	<table>
		<tablename>Milieu</tablename>
		<postgretablename>art_millieu</postgretablename>
		<champs>
			<champ>
				<name>IdMilieu</name>
				<type>integer</type>
				<postgrename>id</postgrename>
				<postgretype>integer</postgretype>
			</champ>
			<champ>
				<name>LibelleMilieu</name>
				<type>text</type>
				<postgrename>libelle</postgrename>
				<postgretype>text</postgretype>
			</champ>
		</champs>
	</table>
	<table>
		<tablename>TypeSortie</tablename>
		<postgretablename>art_type_sortie</postgretablename>
		<champs>
			<champ>
				<name>CodeTypeSortie</name>
				<type>integer</type>
				<postgrename>id</postgrename>
				<postgretype>integer</postgretype>
			</champ>
			<champ>
				<name>LibelleTypeSortie</name>
				<type>text</type>
				<postgrename>libelle</postgrename>
				<postgretype>text</postgretype>
			</champ>
		</champs>
	</table>	
	<table>
		<tablename>Vent</tablename>
		<postgretablename>art_vent</postgretablename>
		<champs>
			<champ>
				<name>CodeVent</name>
				<type>integer</type>
				<postgrename>id</postgrename>
				<postgretype>integer</postgretype>
			</champ>
			<champ>
				<name>LibelleVent</name>
				<type>text</type>
				<postgrename>libelle</postgrename>
				<postgretype>text</postgretype>
			</champ>
		</champs>
	</table>	
	<table>
		<tablename>GrandTypeEngin</tablename>
		<postgretablename>art_grand_type_engin</postgretablename>
		<champs>
			<champ>
				<name>CodeGrandTypeEngin</name>
				<type>text</type>
				<postgrename>id</postgrename>
				<postgretype>text</postgretype>
			</champ>
			<champ>
				<name>LibelleGrandTypeEngin</name>
				<type>text</type>
				<postgrename>libelle</postgrename>
				<postgretype>text</postgretype>
			</champ>
		</champs>
	</table>		
	<table>
		<tablename>TypeEngin</tablename>
		<postgretablename>art_type_engin</postgretablename>
		<champs>
			<champ>
				<name>CodeTypeEngin</name>
				<type>text</type>
				<postgrename>id</postgrename>
				<postgretype>text</postgretype>
			</champ>
			<champ>
				<name>LibelleTypeEngin</name>
				<type>text</type>
				<postgrename>libelle</postgrename>
				<postgretype>text</postgretype>
			</champ>
			<champ>
				<name>CodeGrandTypeEngin</name>
				<type>text</type>
				<postgrename>art_grand_type_engin_id</postgrename>
				<postgretype>text</postgretype>
			</champ>
		</champs>
	</table>	
	<table>
		<tablename>Agglomeration</tablename>
		<postgretablename>art_agglomeration</postgretablename>
		<champs>
			<champ>
				<name>IdAgglo</name>
				<type>integer</type>
				<postgrename>id</postgrename>
				<postgretype>integer</postgretype>
			</champ>
			<champ>
				<name>IdTypeAgglo</name>
				<type>integer</type>
				<postgrename>art_type_agglomeration_id</postgrename>
				<postgretype>integer</postgretype>
			</champ>
			<champ>
				<name>NumeroSecteur</name>
				<type>integer</type>
				<postgrename>ref_secteur_id</postgrename>
				<postgretype>integer</postgretype>
			</champ>
			<champ>
				<name>NomAgglo</name>
				<type>text</type>
				<postgrename>nom</postgrename>
				<postgretype>text</postgretype>
			</champ>
			<champ>
				<name>LongitudeAgglo</name>
				<type>text</type>
				<postgrename>longitude</postgrename>
				<postgretype>text</postgretype>
			</champ>
			<champ>
				<name>LatitudeAgglo</name>
				<type>text</type>
				<postgrename>latitude</postgrename>
				<postgretype>text</postgretype>
			</champ>
			<champ>
				<name>Commentaire</name>
				<type>text</type>
				<postgrename>memo</postgrename>
				<postgretype>text</postgretype>
			</champ>
		</champs>
	</table>
	<table>
		<tablename>OrigineKb</tablename>
		<postgretablename>ref_origine_kb</postgretablename>
		<champs>
			<champ>
				<name>CodeOrigineKb</name>
				<type>integer</type>
				<postgrename>id</postgrename>
				<postgretype>integer</postgretype>
			</champ>
			<champ>
				<name>LibelleOrigineKb</name>
				<type>text</type>
				<postgrename>libelle</postgrename>
				<postgretype>text</postgretype>
			</champ>
		</champs>
	</table>
	<table>
		<tablename>CorrespondanceMaille</tablename>
		<postgretablename>ACCESS</postgretablename>
		<champs>
			<champ>
				<name>doigts</name>
				<type>integer</type>
				<postgrename>ACCESS</postgrename>
				<postgretype>ACCESS</postgretype>
			</champ>
			<champ>
				<name>mm</name>
				<type>integer</type>
				<postgrename>ACCESS</postgrename>
				<postgretype>ACCESS</postgretype>
			</champ>
		</champs>
	</table>
	<table>
		<tablename>Enqueteur</tablename>
		<postgretablename>ACCESS</postgretablename>
		<champs>
			<champ>
				<name>IdEnqueteur</name>
				<type>integer</type>
				<postgrename>ACCESS</postgrename>
				<postgretype>ACCESS</postgretype>
			</champ>
			<champ>
				<name>NomEnqueteur</name>
				<type>text</type>
				<postgrename>ACCESS</postgrename>
				<postgretype>ACCESS</postgretype>
			</champ>
			<champ>
				<name>IdAgglo</name>
				<type>integer</type>
				<postgrename>ACCESS</postgrename>
				<postgretype>ACCESS</postgretype>
			</champ>
		</champs>
	</table>
	<table>
		<tablename>EspeceTMO</tablename>
		<postgretablename>ACCESS</postgretablename>
		<champs>
			<champ>
				<name>esp</name>
				<type>text</type>
				<postgrename>ACCESS</postgrename>
				<postgretype>ACCESS</postgretype>
			</champ>
			<champ>
				<name>tmax</name>
				<type>real</type>
				<postgrename>ACCESS</postgrename>
				<postgretype>ACCESS</postgretype>
			</champ>
			<champ>
				<name>wmax</name>
				<type>real</type>
				<postgrename>ACCESS</postgrename>
				<postgretype>ACCESS</postgretype>
			</champ>
			<champ>
				<name>numSyst</name>
				<type>integer</type>
				<postgrename>ACCESS</postgrename>
				<postgretype>ACCESS</postgretype>
			</champ>
		</champs>
	</table>
	<table>
		<tablename>Secteur</tablename>
		<postgretablename>ref_secteur</postgretablename>
		<champs>
			<champ>
			<name>NumeroSecteur</name>
				<type>integer</type>
				<postgrename>id</postgrename>
				<postgretype>integer</postgretype>
			</champ>
			<champ>
				<name>IdSysteme</name>
				<type>integer</type>
				<postgrename>ref_systeme_id</postgrename>
				<postgretype>integer</postgretype>
			</champ>
			<champ>
				<name>ZDelta</name>
				<type>integer</type>
				<postgrename>id_dans_systeme</postgrename>
				<postgretype>integer</postgretype>
			</champ>
			<champ>
				<name>NomSecteur</name>
				<type>text</type>
				<postgrename>nom</postgrename>
				<postgretype>text</postgretype>
			</champ>
			<champ>
				<name>SuperficieSecteur</name>
				<type>real</type>
				<postgrename>superficie</postgrename>
				<postgretype>real</postgretype>
			</champ>
		</champs>
	</table>
	<table>
		<tablename>Systeme</tablename>
		<postgretablename>ref_systeme</postgretablename>
		<champs>
			<champ>
				<name>IdSysteme</name>
				<type>integer</type>
				<postgrename>id</postgrename>
				<postgretype>integer</postgretype>
			</champ>
			<champ>
				<name>NomSysteme</name>
				<type>text</type>
				<postgrename>libelle</postgrename>
				<postgretype>text</postgretype>
			</champ>
			<champ>
				<name>CodePays</name>
				<type>text</type>
				<postgrename>ref_pays_id</postgrename>
				<postgretype>text</postgretype>
			</champ>
			<champ>
				<name>SuperficieSysteme</name>
				<type>real</type>
				<postgrename>superficie</postgrename>
				<postgretype>real</postgretype>
			</champ>
		</champs>
	</table>
	<table>
		<tablename>Pays</tablename>
		<postgretablename>ref_pays</postgretablename>
		<champs>
			<champ>
				<name>CodePays</name>
				<type>text</type>
				<postgrename>id</postgrename>
				<postgretype>text</postgretype>
			</champ>
			<champ>
				<name>NomPays</name>
				<type>text</type>
				<postgrename>nom</postgrename>
				<postgretype>text</postgretype>
			</champ>
		</champs>
	</table>
	<table>
		<tablename>Nom</tablename>
		<postgretablename>ref_espece</postgretablename>
		<champs>
			<champ>
				<name>CodeNom</name>
				<type>integer</type>
				<postgrename>CALCULAUTO</postgrename>
				<postgretype>integer</postgretype>
			</champ>
			<champ>
			<name>CodeEspece</name>
				<type>text</type>
				<postgrename>id</postgrename>
				<postgretype>text</postgretype>
			</champ>
			<champ>
			<name>LibelleNom</name>
				<type>text</type>
				<postgrename>libelle</postgrename>
				<postgretype>text</postgretype>
			</champ>
			<champ>
			<name>InfoNom</name>
				<type>text</type>
				<postgrename>ACCESS</postgrename>
				<postgretype>text</postgretype>
				<valdefaut>vide</valdefaut>
			</champ>			
		</champs>
	</table>
	<table>
		<tablename>CategorieEcologique</tablename>
		<postgretablename>ref_categorie_ecologique</postgretablename>
		<champs>
			<champ>
			<name>CodeCategorieEcolo</name>
				<type>text</type>
				<postgrename>id</postgrename>
				<postgretype>text</postgretype>
			</champ>
			<champ>
				<name>LibelleCatEcolo</name>
				<type>text</type>
				<postgrename>libelle</postgrename>
				<postgretype>text</postgretype>
			</champ>			
		</champs>
	</table>
	<table>
		<tablename>Categorietrophique</tablename>
		<postgretablename>ref_categorie_trophique</postgretablename>
		<champs>
			<champ>
			<name>CodeCategorieTroph</name>
				<type>text</type>
				<postgrename>id</postgrename>
				<postgretype>text</postgretype>
			</champ>
			<champ>
				<name>LibelleCatTroph</name>
				<type>text</type>
				<postgrename>libelle</postgrename>
				<postgretype>text</postgretype>
			</champ>			
		</champs>
	</table>
	<table>
		<tablename>Espece</tablename>
		<postgretablename>ref_espece</postgretablename>
		<champs>
			<champ>
			<name>CodeEspece</name>
				<type>text</type>
				<postgrename>id</postgrename>
				<postgretype>text</postgretype>
			</champ>
			<champ>
				<name>CodeCategorieTroph</name>
				<type>text</type>
				<postgrename>ref_categorie_trophique_id</postgrename>
				<postgretype>text</postgretype>
			</champ>			
			<champ>
				<name>CodeCategorieEcolo</name>
				<type>text</type>
				<postgrename>ref_categorie_ecologique_id</postgrename>
				<postgretype>text</postgretype>
			</champ>	
			<champ>
			<name>CodeFamille</name>
				<type>integer</type>
				<postgrename>ref_famille_id</postgrename>
				<postgretype>integer</postgretype>
			</champ>
			<champ>
				<name>NonPoisson</name>
				<type>boolean</type>
				<postgrename>non_poisson</postgrename>
				<postgretype>boolean</postgretype>
				<valdefaut>0</valdefaut>
			</champ>
		</champs>
	</table>
	<table>
		<tablename>Famille</tablename>
		<postgretablename>ref_famille</postgretablename>
		<champs>
			<champ>
			<name>CodeFamille</name>
				<type>integer</type>
				<postgrename>id</postgrename>
				<postgretype>integer</postgretype>
			</champ>
			<champ>
				<name>CodeOrdre</name>
				<type>integer</type>
				<postgrename>ref_ordre_id</postgrename>
				<postgretype>integer</postgretype>
			</champ>			
			<champ>
				<name>LibelleFamille</name>
				<type>text</type>
				<postgrename>libelle</postgrename>
				<postgretype>text</postgretype>
			</champ>
		</champs>
	</table>
	<table>
		<tablename>Ordre</tablename>
		<postgretablename>ref_ordre</postgretablename>
		<champs>
			<champ>
				<name>CodeOrdre</name>
				<type>integer</type>
				<postgrename>id</postgrename>
				<postgretype>integer</postgretype>
			</champ>
			<champ>
				<name>LibelleOrdre</name>
				<type>text</type>
				<postgrename>libelle</postgrename>
				<postgretype>text</postgretype>
			</champ>
		</champs>
	</table>
</tables>
